{"cameraMode":{"drawMode":0,"name":"Shaded","section":"Shading Mode"},"sceneLighting":false,"audioPlay":false,"sceneViewState":{"m_AlwaysRefresh":false,"showFog":true,"showSkybox":false,"showFlares":true,"showImageEffects":true,"showParticleSystems":true,"showVisualEffectGraphs":true,"m_FxEnabled":true},"in2DMode":false,"pivot":{"x":0.9395656585693359,"y":0.10000002384185791,"z":0.0},"rotation":{"x":-0.009042331948876381,"y":-0.6787148118019104,"z":0.008352099917829037,"w":-0.7342907190322876},"size":2.459512233734131,"orthographic":false}